_django/__init__.py
_django/_django.py
_django/base_template/__init__.py
_django/base_template/gitignore.example
_heroku/__init__.py
_heroku/_heroku.py
_heroku/base_template/Procfile.example
_heroku/base_template/__init__.py
_template/__init__.py
_template/template.py
_user/__init__.py
_user/_user.py
_user/base_template/__init__.py
_user/base_template/admin.py
_user/base_template/apps.py
_user/base_template/manager.py
_user/base_template/models.py
_user/base_template/serializers.py
django_rest_starter/__init__.py
django_rest_starter/__main__.py
django_rest_starter/_settings.py
django_rest_starter/_venv.py
django_rest_starter/requirements.json
django_rest_starter/settings.json
django_rest_starter-1.0.0.dist-info/LICENSE
django_rest_starter-1.0.0.dist-info/METADATA
django_rest_starter-1.0.0.dist-info/WHEEL
django_rest_starter-1.0.0.dist-info/entry_points.txt
django_rest_starter-1.0.0.dist-info/top_level.txt
django_rest_starter-1.0.0.dist-info/RECORD
