Metadata-Version: 2.1
Name: django-rest-starter
Version: 1.0.0
Summary: Package to start a django with rest
Home-page: https://github.com/LeonardoCruzx/django-rest-starter
Author: Leonardo Cruz
Author-email: leonardo.m.cruz0@gmail.com
License: UNKNOWN
Platform: UNKNOWN
Requires-Python: >=3.7
